Annotations2Sub/Annotations.py
Annotations2Sub/__dummy__.py
Annotations2Sub/__init__.py
Annotations2Sub/__main__.py
Annotations2Sub/__version__.py
Annotations2Sub/_main.py
Annotations2Sub/cli.py
Annotations2Sub/cli_utils.py
Annotations2Sub/color.py
Annotations2Sub/convert.py
Annotations2Sub/flags.py
Annotations2Sub/i18n.py
Annotations2Sub/py.typed
Annotations2Sub/utils.py
Annotations2Sub/locales/en/LC_MESSAGES/Annotations2Sub.mo
Annotations2Sub/locales/zh/LC_MESSAGES/Annotations2Sub.mo
Annotations2Sub/subtitles/CONSTANT.py
Annotations2Sub/subtitles/__init__.py
Annotations2Sub/subtitles/draw.py
Annotations2Sub/subtitles/event.py
Annotations2Sub/subtitles/info.py
Annotations2Sub/subtitles/style.py
Annotations2Sub/subtitles/subtitles.py
Annotations2Sub/subtitles/tag.py
Annotations2Sub/subtitles/utils.py
annotations2sub-2.24.0.dist-info/licenses/LICENSE
annotations2sub-2.24.0.dist-info/METADATA
annotations2sub-2.24.0.dist-info/WHEEL
annotations2sub-2.24.0.dist-info/entry_points.txt
annotations2sub-2.24.0.dist-info/top_level.txt
annotations2sub-2.24.0.dist-info/RECORD
