Metadata-Version: 2.4
Name: Annotations2Sub
Version: 2.24.0
Summary: Convert Youtube Annotations to subtitles.
Author-email: 我如天翼 <wrtyis@outlook.com>
License-Expression: GPL-3.0-or-later
Project-URL: Homepage, https://github.com/USED255/Annotations2Sub
Project-URL: Bug Tracker, https://github.com/USED255/Annotations2Sub/issues
Keywords: Youtube,Annotations,Subtitles,Converter
Classifier: Programming Language :: Python :: 3 :: Only
Classifier: Programming Language :: Python :: 3.7
Classifier: Programming Language :: Python :: 3.8
Classifier: Programming Language :: Python :: 3.9
Classifier: Programming Language :: Python :: 3.10
Classifier: Programming Language :: Python :: 3.11
Classifier: Programming Language :: Python :: 3.12
Classifier: Programming Language :: Python :: 3.13
Classifier: Programming Language :: Python :: 3.14
Classifier: Programming Language :: Python :: Implementation :: PyPy
Classifier: Programming Language :: Python :: Implementation :: CPython
Classifier: Operating System :: OS Independent
Classifier: Development Status :: 5 - Production/Stable
Classifier: Environment :: Console
Classifier: Natural Language :: Chinese (Simplified)
Classifier: Natural Language :: English
Classifier: Typing :: Typed
Requires-Python: >=3.7
License-File: LICENSE
Dynamic: license-file
